tap_clientsuccess/__init__.py
tap_clientsuccess/client.py
tap_clientsuccess/schemas/client.json
tap_clientsuccess/schemas/clients.json
tap_clientsuccess/schemas/interactions.json
tap_clientsuccess/streams.py
tap_clientsuccess/tap.py
tap_clientsuccess/tests/__init__.py
tap_clientsuccess/tests/test_core.py
tap_clientsuccess-0.0.1.dist-info/entry_points.txt
tap_clientsuccess-0.0.1.dist-info/WHEEL
tap_clientsuccess-0.0.1.dist-info/METADATA
tap_clientsuccess-0.0.1.dist-info/RECORD
